{
  "project_info": {
    "project_number": "759044812663",
    "project_id": "family-flow-app-4900a",
    "storage_bucket": "family-flow-app-4900a.firebasestorage.app"
  },
  "client": [
    {
      "client_info": {
        "mobilesdk_app_id": "1:759044812663:android:fd28ea5690071b8e787b72",
        "android_client_info": {
          "package_name": "com.example.family_flow_app_client"
        }
      },
      "oauth_client": [],
      "api_key": [
        {
          "current_key": "AIzaSyDa6SFdj1gvamcmGPTa5sk4QmaHiPWYNvI"
        }
      ],
      "services": {
        "appinvite_service": {
          "other_platform_oauth_client": []
        }
      }
    }
  ],
  "configuration_version": "1"
}